stats/__init__.py
stats/apps.py
stats/conf.py
stats/connections.py
stats/objects.py
stats/mixins/__init__.py
stats/mixins/see_stats.py
stats/mixins/stats.py
tests/__init__.py
tests/settings.py
tests/test_models.py
django_stats_redis-0.1.1.dist-info/AUTHORS.rst
django_stats_redis-0.1.1.dist-info/LICENSE
django_stats_redis-0.1.1.dist-info/METADATA
django_stats_redis-0.1.1.dist-info/WHEEL
django_stats_redis-0.1.1.dist-info/top_level.txt
django_stats_redis-0.1.1.dist-info/RECORD
