Metadata-Version: 2.1
Name: django-stats-redis
Version: 0.1.1
Summary: Manage stats within Redis for Django models
Home-page: https://github.com/exolever/django-stats
Author: marfyl
Author-email: marfyl.dev@gmail.com
License: MIT
Keywords: python,django,stats,redis
Platform: UNKNOWN
Classifier: Development Status :: 5 - Production/Stable
Classifier: Environment :: Web Environment
Classifier: Framework :: Django :: 1.11
Classifier: Framework :: Django :: 2.0
Classifier: Intended Audience :: Developers
Classifier: License :: OSI Approved :: BSD License
Classifier: Natural Language :: English
Classifier: Operating System :: OS Independent
Classifier: Programming Language :: Python :: Implementation :: PyPy
Classifier: Programming Language :: Python
Classifier: Programming Language :: Python :: 3.6
Requires-Dist: django-appconf
Requires-Dist: redis
